CHANGES.txt
LICENSE.txt
MANIFEST.in
README.txt
setup.py
js/__init__.py
js.jquery_flot.egg-info/PKG-INFO
js.jquery_flot.egg-info/SOURCES.txt
js.jquery_flot.egg-info/dependency_links.txt
js.jquery_flot.egg-info/entry_points.txt
js.jquery_flot.egg-info/namespace_packages.txt
js.jquery_flot.egg-info/not-zip-safe
js.jquery_flot.egg-info/requires.txt
js.jquery_flot.egg-info/top_level.txt
js/jquery_flot/__init__.py
js/jquery_flot/test_flot.txt
js/jquery_flot/resources/excanvas.js
js/jquery_flot/resources/excanvas.min.js
js/jquery_flot/resources/jquery.colorhelpers.js
js/jquery_flot/resources/jquery.colorhelpers.min.js
js/jquery_flot/resources/jquery.flot.canvas.js
js/jquery_flot/resources/jquery.flot.canvas.min.js
js/jquery_flot/resources/jquery.flot.categories.js
js/jquery_flot/resources/jquery.flot.categories.min.js
js/jquery_flot/resources/jquery.flot.crosshair.js
js/jquery_flot/resources/jquery.flot.crosshair.min.js
js/jquery_flot/resources/jquery.flot.errorbars.js
js/jquery_flot/resources/jquery.flot.errorbars.min.js
js/jquery_flot/resources/jquery.flot.fillbetween.js
js/jquery_flot/resources/jquery.flot.fillbetween.min.js
js/jquery_flot/resources/jquery.flot.image.js
js/jquery_flot/resources/jquery.flot.image.min.js
js/jquery_flot/resources/jquery.flot.js
js/jquery_flot/resources/jquery.flot.min.js
js/jquery_flot/resources/jquery.flot.navigate.js
js/jquery_flot/resources/jquery.flot.navigate.min.js
js/jquery_flot/resources/jquery.flot.pie.js
js/jquery_flot/resources/jquery.flot.pie.min.js
js/jquery_flot/resources/jquery.flot.resize.js
js/jquery_flot/resources/jquery.flot.resize.min.js
js/jquery_flot/resources/jquery.flot.selection.js
js/jquery_flot/resources/jquery.flot.selection.min.js
js/jquery_flot/resources/jquery.flot.stack.js
js/jquery_flot/resources/jquery.flot.stack.min.js
js/jquery_flot/resources/jquery.flot.symbol.js
js/jquery_flot/resources/jquery.flot.symbol.min.js
js/jquery_flot/resources/jquery.flot.threshold.js
js/jquery_flot/resources/jquery.flot.threshold.min.js
js/jquery_flot/resources/jquery.flot.time.js
js/jquery_flot/resources/jquery.flot.time.min.js