Metadata-Version: 1.0
Name: js.jquery-flot
Version: 0.8.1
Summary: Fanstatic packaging of flot
Home-page: UNKNOWN
Author: Fanstatic Developers
Author-email: fanstatic@googlegroups.com
License: BSD
Platform: UNKNOWN
